localscope/__init__.py
tests/test_localscope.py
localscope-0.2.5.dist-info/LICENSE
localscope-0.2.5.dist-info/METADATA
localscope-0.2.5.dist-info/WHEEL
localscope-0.2.5.dist-info/top_level.txt
localscope-0.2.5.dist-info/RECORD
