Metadata-Version: 2.2
Name: localscope
Version: 0.2.5
Summary: Restrict the scope of functions for reproducible code execution and peace of mind.
Author: Till Hoffmann
Project-URL: Documentation, https://localscope.readthedocs.io
Project-URL: Repository, https://github.com/tillahoffmann/localscope.git
Project-URL: Issues, https://github.com/tillahoffmann/localscope/issues
Classifier: Development Status :: 4 - Beta
Classifier: License :: OSI Approved :: MIT License
Requires-Python: >=3.8
License-File: LICENSE
